[{"_id":"5e6d9dfbf7b4f1001a901c34","link":"https://torrenthall10.com/post/28614","title":"킹덤 시즌2 Kingdom.2019.KOREAN.S02.1080p.NF.WEBRip.DDP5.1.Atmos.x264-NTG","size":null,"thumbnail":{"public_id":"r7bmokce6tgu6veu7dqv","version":1584242166,"signature":"29fbef4c030fed0b3e2a82239535e440e3d7c6e0","width":200,"height":296,"format":"jpg","resource_type":"image","created_at":"2020-03-15T03:16:06Z","tags":[],"bytes":34219,"type":"upload","etag":"fbf43e1c5d27eeee42476df80e34e09a","placeholder":false,"url":"http://res.cloudinary.com/dv5ki1m4h/image/upload/v1584242166/r7bmokce6tgu6veu7dqv.jpg","secure_url":"https://res.cloudinary.com/dv5ki1m4h/image/upload/v1584242166/r7bmokce6tgu6veu7dqv.jpg","backup_url":"api.cloudinary.com/v1_1/dv5ki1m4h/resources/6949e523c2235dd33e68ca8fb9b5984c/backup/6ff19cffbb335b91a5c9811a78367444","access_mode":"public"},"type":-1,"views":0,"category":"Movies","like":0,"dislike":0,"data":"3-15","torrent_id":10},{"_id":"5e6d9decf7b4f1001a901c32","link":"https://torrenthall10.com/post/27945","title":"1917 (2019) (1080p AMZN WEB-DL x265 HEVC 10bit AC3 5.1 Qman) [UTR]","size":null,"thumbnail":{"public_id":"zg7i4lw5wqks1bjgxt3q","version":1584242150,"signature":"c24b86f49507dbcd62e9670297ee3e5563459e99","width":200,"height":286,"format":"jpg","resource_type":"image","created_at":"2020-03-15T03:15:50Z","tags":[],"bytes":26937,"type":"upload","etag":"fed3c6c53a962be3197adbded517a5d0","placeholder":false,"url":"http://res.cloudinary.com/dv5ki1m4h/image/upload/v1584242150/zg7i4lw5wqks1bjgxt3q.jpg","secure_url":"https://res.cloudinary.com/dv5ki1m4h/image/upload/v1584242150/zg7i4lw5wqks1bjgxt3q.jpg","backup_url":"api.cloudinary.com/v1_1/dv5ki1m4h/resources/0364382e6ff2f395ddf79d75af9099a9/backup/2e3afefac83d1c08015a3f39aa73a21b","access_mode":"public"},"type":-1,"views":0,"category":"Movies","like":0,"dislike":0,"data":"3-15","torrent_id":9},{"_id":"5e6d9dddf7b4f1001a901c30","link":"https://torrenthall10.com/post/27940","title":"작은 아씨들 Little Women (2019) (1080p AMZN Webrip x265 10bit EAC3 5.1 - Ic…","size":null,"thumbnail":{"public_id":"q9kptcd5ifu63kxeclc4","version":1584242136,"signature":"bdcc5336e4fda5860584d4dba6284a1fcf559bb7","width":200,"height":287,"format":"jpg","resource_type":"image","created_at":"2020-03-15T03:15:36Z","tags":[],"bytes":21901,"type":"upload","etag":"2907e5270c190cc43d0573154d564768","placeholder":false,"url":"http://res.cloudinary.com/dv5ki1m4h/image/upload/v1584242136/q9kptcd5ifu63kxeclc4.jpg","secure_url":"https://res.cloudinary.com/dv5ki1m4h/image/upload/v1584242136/q9kptcd5ifu63kxeclc4.jpg","backup_url":"api.cloudinary.com/v1_1/dv5ki1m4h/resources/61b4d10ec890dd948acf44f212c5aaec/backup/8eadd70db750b886ff4b88f0ee3730c9","access_mode":"public"},"type":-1,"views":0,"category":"Movies","like":0,"dislike":0,"data":"3-15","torrent_id":8},{"_id":"5e6d9dcef7b4f1001a901c2e","link":"https://torrenthall10.com/post/27938","title":"[자체한글/자석] 버즈 오브 프레이, 할리 퀸의 황홀한 해방 Birds.of.Prey.2020.1080p.HDRip.x264.…","size":null,"thumbnail":{"public_id":"qzf5ebwncak0a1ec6wzx","version":1584242121,"signature":"515bb361508328c71913f4d2f753100e8df92d9f","width":200,"height":285,"format":"jpg","resource_type":"image","created_at":"2020-03-15T03:15:21Z","tags":[],"bytes":43844,"type":"upload","etag":"55a49165aa79800e9d7afbb2f72b6d20","placeholder":false,"url":"http://res.cloudinary.com/dv5ki1m4h/image/upload/v1584242121/qzf5ebwncak0a1ec6wzx.jpg","secure_url":"https://res.cloudinary.com/dv5ki1m4h/image/upload/v1584242121/qzf5ebwncak0a1ec6wzx.jpg","backup_url":"api.cloudinary.com/v1_1/dv5ki1m4h/resources/b6fa99b8d2a775bdaf5eaf17e9515079/backup/86489889dc760361856435c7bf2a7790","access_mode":"public"},"type":-1,"views":0,"category":"Movies","like":0,"dislike":0,"data":"3-15","torrent_id":7},{"_id":"5e6d9dbff7b4f1001a901c2c","link":"https://torrenthall10.com/post/27931","title":"부탁 하나만 들어줘 A.Simple.Favor.2018.OAR.1080p.BluRay.H264.AAC-RARBG","size":null,"thumbnail":{"public_id":"xszwi4bdmortzxdqymhq","version":1584242106,"signature":"24266c5bb316377e6abd49e1395387cdf8cc6ae3","width":200,"height":286,"format":"jpg","resource_type":"image","created_at":"2020-03-15T03:15:06Z","tags":[],"bytes":21652,"type":"upload","etag":"9448580fe224e43532f9b492e3ebc844","placeholder":false,"url":"http://res.cloudinary.com/dv5ki1m4h/image/upload/v1584242106/xszwi4bdmortzxdqymhq.jpg","secure_url":"https://res.cloudinary.com/dv5ki1m4h/image/upload/v1584242106/xszwi4bdmortzxdqymhq.jpg","backup_url":"api.cloudinary.com/v1_1/dv5ki1m4h/resources/96fa550a79be0321b7080676edf8be83/backup/b53f18a685fd514a2db12653ee326941","access_mode":"public"},"type":-1,"views":0,"category":"Movies","like":0,"dislike":0,"data":"3-15","torrent_id":6},{"_id":"5e6d9db0f7b4f1001a901c2a","link":"https://torrenthall10.com/post/27704","title":"[개봉예정] 아일랜드 The.Island.2018.CHINESE.1080p.BluRay.H264.AAC-VXT","size":null,"thumbnail":{"public_id":"vwbbvwohebm4err1e694","version":1584242091,"signature":"c1632d5a2ec15c852737de8f7e8a76ffbc156b4a","width":200,"height":286,"format":"jpg","resource_type":"image","created_at":"2020-03-15T03:14:51Z","tags":[],"bytes":21322,"type":"upload","etag":"3ed7ba85bb933dc00b53ff365f058494","placeholder":false,"url":"http://res.cloudinary.com/dv5ki1m4h/image/upload/v1584242091/vwbbvwohebm4err1e694.jpg","secure_url":"https://res.cloudinary.com/dv5ki1m4h/image/upload/v1584242091/vwbbvwohebm4err1e694.jpg","backup_url":"api.cloudinary.com/v1_1/dv5ki1m4h/resources/edcd8ce55cee1c88a33a1ee195f4167f/backup/bd19eda1d8abb8183857ef637bee6600","access_mode":"public"},"type":-1,"views":0,"category":"Movies","like":0,"dislike":0,"data":"3-15","torrent_id":5},{"_id":"5e6d9da1f7b4f1001a901c28","link":"https://torrenthall10.com/post/27652","title":"그루지.2020 The.Grudge.2020.1080p.AMZN.WEBRip.DDP5.1.x264-NTG","size":null,"thumbnail":{"public_id":"mmqwedwqy5dn33z7tqmg","version":1584242076,"signature":"b146871a078ed3c17f7b29db976f997cb24cc924","width":200,"height":285,"format":"jpg","resource_type":"image","created_at":"2020-03-15T03:14:36Z","tags":[],"bytes":19515,"type":"upload","etag":"7ba42bb9eb8509f807a8297a7ce3db13","placeholder":false,"url":"http://res.cloudinary.com/dv5ki1m4h/image/upload/v1584242076/mmqwedwqy5dn33z7tqmg.jpg","secure_url":"https://res.cloudinary.com/dv5ki1m4h/image/upload/v1584242076/mmqwedwqy5dn33z7tqmg.jpg","backup_url":"api.cloudinary.com/v1_1/dv5ki1m4h/resources/03a6b05f64691634a366e70750517fcb/backup/fdc502970101045535331c97fe02b59c","access_mode":"public"},"type":-1,"views":0,"category":"Movies","like":0,"dislike":0,"data":"3-15","torrent_id":4},{"_id":"5e6d9d92f7b4f1001a901c26","link":"https://torrenthall10.com/post/27385","title":"주디 Judy.2020.1080p.KOR.FHDRip.H264.AAC-RTM","size":null,"thumbnail":{"public_id":"pvwgekwhjxqglr4iz29e","version":1584242061,"signature":"8ac16cc958f856d12b29e1763d486fdedcc45fd2","width":200,"height":285,"format":"jpg","resource_type":"image","created_at":"2020-03-15T03:14:21Z","tags":[],"bytes":27727,"type":"upload","etag":"bdbbf7773fab6c1d90b8310225038dc2","placeholder":false,"url":"http://res.cloudinary.com/dv5ki1m4h/image/upload/v1584242061/pvwgekwhjxqglr4iz29e.jpg","secure_url":"https://res.cloudinary.com/dv5ki1m4h/image/upload/v1584242061/pvwgekwhjxqglr4iz29e.jpg","backup_url":"api.cloudinary.com/v1_1/dv5ki1m4h/resources/e501d3f83071e8753c85d5ce9fc02037/backup/265441fb0628b1283f74102e6ff03e20","access_mode":"public"},"type":-1,"views":0,"category":"Movies","like":0,"dislike":0,"data":"3-15","torrent_id":3},{"_id":"5e6d9d82f7b4f1001a901c24","link":"https://torrenthall10.com/post/26573","title":"[더빙+영음] 수퍼 소닉 Sonic.the.Hedgehog.2019.1080p.x264.2Audio(Kor,Eng).Sub(K…","size":null,"thumbnail":{"public_id":"bpdxhuqc0tejgn4ixwsy","version":1584242045,"signature":"75755461f5fb77b666c8d7e05ce00d651e8f55a7","width":200,"height":286,"format":"jpg","resource_type":"image","created_at":"2020-03-15T03:14:05Z","tags":[],"bytes":34540,"type":"upload","etag":"0ff2e111d29f6ae3c2a5c0fba2f83375","placeholder":false,"url":"http://res.cloudinary.com/dv5ki1m4h/image/upload/v1584242045/bpdxhuqc0tejgn4ixwsy.jpg","secure_url":"https://res.cloudinary.com/dv5ki1m4h/image/upload/v1584242045/bpdxhuqc0tejgn4ixwsy.jpg","backup_url":"api.cloudinary.com/v1_1/dv5ki1m4h/resources/b249b3702014dcd0b2d97d55047fa52c/backup/a084752de2f71bf5a020f27fd33dcc72","access_mode":"public"},"type":-1,"views":0,"category":"Movies","like":0,"dislike":0,"data":"3-15","torrent_id":2},{"_id":"5e6d9d74f7b4f1001a901c22","link":"https://torrenthall10.com/post/25477","title":"클로젯 The Closet.2020.1080p.FHDRip.H264.AAC-NonDRM","size":null,"thumbnail":{"public_id":"xpfdrymk0scsfokbono1","version":1584242031,"signature":"78f50d4a699a28d19c5d31e7a58e0754f36eea74","width":200,"height":285,"format":"jpg","resource_type":"image","created_at":"2020-03-15T03:13:51Z","tags":[],"bytes":17227,"type":"upload","etag":"9cee526974d2dd26f623f9015c373786","placeholder":false,"url":"http://res.cloudinary.com/dv5ki1m4h/image/upload/v1584242031/xpfdrymk0scsfokbono1.jpg","secure_url":"https://res.cloudinary.com/dv5ki1m4h/image/upload/v1584242031/xpfdrymk0scsfokbono1.jpg","backup_url":"api.cloudinary.com/v1_1/dv5ki1m4h/resources/7f400f4766e45f6936317cd837dbb428/backup/0ccf7b9b9e9e39fdd623409bcea018e3","access_mode":"public"},"type":-1,"views":0,"category":"Movies","like":0,"dislike":0,"data":"3-15","torrent_id":1}]